faker_graphics/__init__.py
faker_graphics/__main__.py
faker_graphics/common.py
faker_graphics/compat.py
faker_graphics/drawing.py
faker_graphics/randomcolor.py
faker_graphics/data/colormap.json
faker_graphics-0.3.0.dist-info/entry_points.txt
faker_graphics-0.3.0.dist-info/LICENSE.txt
faker_graphics-0.3.0.dist-info/WHEEL
faker_graphics-0.3.0.dist-info/METADATA
faker_graphics-0.3.0.dist-info/RECORD
