Metadata-Version: 2.1
Name: faker-graphics
Version: 0.3.0
Summary: Provider for the Faker package to generate placeholder images and more.
Keywords: faker,factory-boy,placeholder,images,colors,cairo
Author-email: Florian Demmer <fdemmer@gmail.com>
Requires-Python: >=3.8
Classifier: Development Status :: 4 - Beta
Classifier: Intended Audience :: Developers
Classifier: License :: OSI Approved :: MIT License
Classifier: Operating System :: OS Independent
Classifier: Programming Language :: Python :: 3
Classifier: Programming Language :: Python :: 3 :: Only
Classifier: Programming Language :: Python :: 3.8
Classifier: Programming Language :: Python :: 3.9
Classifier: Programming Language :: Python :: 3.10
Classifier: Programming Language :: Python :: 3.11
Requires-Dist: faker
Requires-Dist: structlog
Requires-Dist: strenum; python_version < "3.11"
Requires-Dist: cairocffi ; extra == "cairocffi"
Requires-Dist: click ; extra == "cli"
Requires-Dist: sty ; extra == "cli"
Requires-Dist: bumpver ; extra == "dev"
Requires-Dist: pycairo ; extra == "pycairo"
Project-URL: Changelog, https://github.com/fdemmer/faker-graphics/releases
Project-URL: Homepage, https://github.com/fdemmer/faker-graphics
Project-URL: Repository, https://github.com/fdemmer/faker-graphics.git
Provides-Extra: cairocffi
Provides-Extra: cli
Provides-Extra: dev
Provides-Extra: pycairo
